aviatrix_discovery-0.2.148.dist-info/WHEEL
aviatrix_discovery-0.2.148.dist-info/top_level.txt
aviatrix_discovery-0.2.148.dist-info/entry_points.txt
aviatrix_discovery-0.2.148.dist-info/RECORD
aviatrix_discovery-0.2.148.dist-info/METADATA
generator/config.py
generator/generate.cpython-310-x86_64-linux-gnu.so
generator/convert.cpython-310-x86_64-linux-gnu.so
generator/cli.cpython-310-x86_64-linux-gnu.so
generator/log.cpython-310-x86_64-linux-gnu.so
generator/__init__.py
generator/common/__init__.py
generator/common/serializers/load.cpython-310-x86_64-linux-gnu.so
generator/common/serializers/xlsx.cpython-310-x86_64-linux-gnu.so
generator/common/serializers/yaml.cpython-310-x86_64-linux-gnu.so
generator/common/serializers/__init__.py
generator/common/serializers/export.cpython-310-x86_64-linux-gnu.so
generator/data/template.yaml
generator/data/config.yaml
