Metadata-Version: 2.1
Name: aviatrix-discovery
Version: 0.2.148
Summary: Aviatrix Discovery Generator
Home-page: https://docs.aviatrix.com/index.html
Author: Aviatrix Automation
Author-email: aviatrix-automation@aviatrix.com
Project-URL: Changelog, https://github.com/aviatrix-automation/discovery_migration/blob/master/CHANGELOG.rst
Project-URL: Issue Tracker, https://github.com/aviatrix-automation/discovery_migration/issues
Classifier: Development Status :: 4 - Beta
Classifier: Environment :: Console
Classifier: Intended Audience :: Developers
Classifier: Operating System :: POSIX
Classifier: Programming Language :: Python
Classifier: Programming Language :: Python :: 3
Classifier: Programming Language :: Python :: 3 :: Only
Classifier: Programming Language :: Python :: 3.7
Classifier: Programming Language :: Python :: 3.8
Classifier: Programming Language :: Python :: 3.9
Classifier: Programming Language :: Python :: Implementation :: CPython
Classifier: Topic :: Utilities
Requires-Python: >=3.7
Requires-Dist: boto3==1.24.22
Requires-Dist: botocore==1.27.22
Requires-Dist: certifi==2020.12.5
Requires-Dist: chardet==4.0.0
Requires-Dist: decorator==5.0.9
Requires-Dist: idna==2.10
Requires-Dist: jmespath==0.10.0
Requires-Dist: py==1.10.0
Requires-Dist: python-dateutil==2.8.1
Requires-Dist: PyYAML==6.0.2
Requires-Dist: requests==2.25.1
Requires-Dist: retry==0.9.2
Requires-Dist: s3transfer==0.6.0
Requires-Dist: six==1.16.0
Requires-Dist: urllib3==1.26.4
Requires-Dist: xlsxwriter==3.0.1
Requires-Dist: pandas==1.4.3
Requires-Dist: Numpy==1.26.4
Requires-Dist: openpyxl==3.0.7
Requires-Dist: pydantic==1.9.0
Requires-Dist: aviatrix-migration
